MANIFEST.in
setup.py
pest/__init__.py
pest/custom_pest.py
pest/django_pest.py
pest/nose_pest.py
pest/pest.py
pest/pester
pest/runtests_pest.py
pest.egg-info/PKG-INFO
pest.egg-info/SOURCES.txt
pest.egg-info/dependency_links.txt
pest.egg-info/requires.txt
pest.egg-info/top_level.txt
pest/images/fail.png
pest/images/pass.png
pest/images/pending.png