Metadata-Version: 1.0
Name: pest
Version: 1.0.3
Summary: Auto tester for python
Home-page: http://github.com/ccollins/pest
Author: Chuck Collins
Author-email: chuck.collins@gmail.com
License: MIT
Platform: UNKNOWN
